{
  "descricao": "Pessoas e canais de contato importantes para o time de suporte.",
  "items": [ 
    { 
      "id": 1,
      "nome": "Ivan Theis",
      "cargo": "Supervisor",
      "departamento": "Suporte",
      "email": "ivan.theis@multipedidos.com.br",
      "telefone": "+55 51 9873-3116",
      "slack": "Discord: ivantheis",
      "observacao": ""
    },
    {
      "id": 2,
      "nome": "Jonatas Souza",
      "cargo": "Supervisor",
      "departamento": "Suporte",
      "email": "jonatas@multipedidos.com.br",
      "telefone": "+55 21 98408-7200",
      "slack": "Discord: jonatasMP",
      "observacao": ""
    },
    {
      "id": 3,
      "nome": "Elgin",
      "cargo": "Suporte",
      "departamento": "Suporte",
      "email": "",
      "telefone": "+5511998519559",
      "slack": "",
      "observacao": "Chamar no WhatsApp"
    },
    {
      "id": 4,
      "nome": "Comercial Multipedidos",
      "cargo": "Comercial",
      "departamento": "Comercial",
      "email": "comercial@multipedidos.com.br",
      "telefone": "+55 47 99192-5352",
      "slack": "Discord: Comercial",
      "observacao": "Contato para interessados e novos clientes"
    }
  ]
}
